sinapsis_albumentations/__init__.py
sinapsis_albumentations/helpers/__init__.py
sinapsis_albumentations/helpers/tags.py
sinapsis_albumentations/templates/__init__.py
sinapsis_albumentations/templates/albumentations_transforms.py
sinapsis_albumentations-0.1.7.dist-info/licenses/LICENSE
sinapsis_albumentations-0.1.7.dist-info/METADATA
sinapsis_albumentations-0.1.7.dist-info/WHEEL
sinapsis_albumentations-0.1.7.dist-info/top_level.txt
sinapsis_albumentations-0.1.7.dist-info/RECORD
