Metadata-Version: 2.4
Name: sinapsis-albumentations
Version: 0.1.7
Summary: Templates to perform image transformations using the albumentations library.
Author-email: SinapsisAI <dev@sinapsis-ai.com>
Project-URL: Homepage, https://sinapsis.tech
Project-URL: Documentation, https://docs.sinapsis.tech/docs
Project-URL: Tutorials, https://docs.sinapsis.tech/tutorials
Project-URL: Repository, https://github.com/Sinapsis-AI/sinapsis-image-transforms.git
Requires-Python: >=3.10
License-File: LICENSE
Requires-Dist: albumentations==2.0.6
Requires-Dist: sinapsis>=0.1.1
Dynamic: license-file
